.cvsignore
COPYING
INSTALL
INSTALL.sanger
MANIFEST.in
README
TODO.rst
ez_setup.py
setup.py
Poly.egg-info/PKG-INFO
Poly.egg-info/SOURCES.txt
Poly.egg-info/dependency_links.txt
Poly.egg-info/top_level.txt
lib/__init__.py
lib/cat.py
lib/lsf.py
lib/rcp.py
lib/standalone.py
lib/submit.py
lib/watch.py
scripts/polycat
scripts/polyjob
scripts/polylocal
scripts/polyrcp
scripts/polysub
scripts/polywatch
scripts/polyxargs
scripts/polyxjob
test/test_cat.py
test/test_poly.py
test/test_rcp.py
test/test_submit.py
test/test_watch.py
