Metadata-Version: 1.0
Name: Poly
Version: 0.1.1
Summary: rapid development of embarrassingly parallelizable applications
Home-page: http://www.ebi.ac.uk/~hoffman/software/poly/
Author: Michael Hoffman
Author-email: hoffman@ebi.ac.uk
License: GNU GPLv2
Download-URL: http://www.ebi.ac.uk/~hoffman/software/poly//Poly-0.1.1.tar.gz
Platform: any
Classifier: Development Status :: 3 - Alpha
Classifier: Intended Audience :: Developers
Classifier: Intended Audience :: Science/Research
Classifier: License :: OSI Approved :: GNU General Public License (GPL)
Classifier: Natural Language :: English
Classifier: Programming Language :: Python
Classifier: Topic :: System :: Distributed Computing
